{"GlobalPropertiesHash":"ftM7mEOIu2uvLq9EVJEjzht1xen3e+QThezgiZ1rNBM=","FingerprintPatternsHash":"gq3WsqcKBUGTSNle7RKKyXRIwh7M8ccEqOqYvIzoM04=","PropertyOverridesHash":"8ZRc1sGeVrPBx4lD717BgRaQekyh78QKV9SKsdt638U=","InputHashes":["5COqgI0E6rx1DBGa943WagtQJ8/Fa9xUWZhoEaJcfT8=","HfPGjRrRpIvf4ZeewZGQBY\u002BlfaZKuVqzpvtxGcpN/wE=","vBDjKrTA37WEEvbOiE30z4WwYcSaoHiv\u002BVe/pGRebaw=","6DNUHqUJamGuzm9BfBEY\u002Bdy9CuCczQLO/d\u002B6mXa3vH8=","Bwps20IR269pNgeOYqWYrUhUWY2KnE0/MluM4lIZN9w=","JR2/9ee5GcpqRBbxpcQXBjdpPgMK9\u002BNmdr7JGEFPt9Q="],"CachedAssets":{"5COqgI0E6rx1DBGa943WagtQJ8/Fa9xUWZhoEaJcfT8=":{"Identity":"D:\\Back-end_CuoiKy\\Nam3\\lap-trinh-web\\wwwroot\\dashboard.html","SourceId":"lap_trinh_web","SourceType":"Discovered","ContentRoot":"D:\\Back-end_CuoiKy\\Nam3\\lap-trinh-web\\wwwroot\\","BasePath":"_content/lap_trinh_web","RelativePath":"dashboard#[.{fingerprint}]?.html","AssetKind":"All","AssetMode":"All","AssetRole":"Primary","AssetMergeBehavior":null,"AssetMergeSource":"","RelatedAsset":null,"AssetTraitName":null,"AssetTraitValue":null,"Fingerprint":"7h0wxlpvgr","Integrity":"lbAtCM4tDNvN\u002BxH9GCZxFYLGQUKwSB9fE2cbJX2saZE=","CopyToOutputDirectory":"Never","CopyToPublishDirectory":"PreserveNewest","OriginalItemSpec":"wwwroot\\dashboard.html","FileLength":655,"LastWriteTime":"2026-03-05T15:57:52.6044263+00:00"},"HfPGjRrRpIvf4ZeewZGQBY\u002BlfaZKuVqzpvtxGcpN/wE=":{"Identity":"D:\\Back-end_CuoiKy\\Nam3\\lap-trinh-web\\wwwroot\\index.html","SourceId":"lap_trinh_web","SourceType":"Discovered","ContentRoot":"D:\\Back-end_CuoiKy\\Nam3\\lap-trinh-web\\wwwroot\\","BasePath":"_content/lap_trinh_web","RelativePath":"index#[.{fingerprint}]?.html","AssetKind":"All","AssetMode":"All","AssetRole":"Primary","AssetMergeBehavior":null,"AssetMergeSource":"","RelatedAsset":null,"AssetTraitName":null,"AssetTraitValue":null,"Fingerprint":"qxq8xooh92","Integrity":"ouRP\u002BqbmBqDpEfcagM\u002BIDDJ457nUWVHZPzzcDp\u002BF\u002BhU=","CopyToOutputDirectory":"Never","CopyToPublishDirectory":"PreserveNewest","OriginalItemSpec":"wwwroot\\index.html","FileLength":2326,"LastWriteTime":"2026-03-05T16:02:40.9570812+00:00"},"vBDjKrTA37WEEvbOiE30z4WwYcSaoHiv\u002BVe/pGRebaw=":{"Identity":"D:\\Back-end_CuoiKy\\Nam3\\lap-trinh-web\\wwwroot\\sanpham.html","SourceId":"lap_trinh_web","SourceType":"Discovered","ContentRoot":"D:\\Back-end_CuoiKy\\Nam3\\lap-trinh-web\\wwwroot\\","BasePath":"_content/lap_trinh_web","RelativePath":"sanpham#[.{fingerprint}]?.html","AssetKind":"All","AssetMode":"All","AssetRole":"Primary","AssetMergeBehavior":null,"AssetMergeSource":"","RelatedAsset":null,"AssetTraitName":null,"AssetTraitValue":null,"Fingerprint":"o63z6onjp8","Integrity":"IK87h5Cw/vCpJfdJyBtf0BBeuytu4Vmlh4yON9QfWG0=","CopyToOutputDirectory":"Never","CopyToPublishDirectory":"PreserveNewest","OriginalItemSpec":"wwwroot\\sanpham.html","FileLength":7488,"LastWriteTime":"2026-03-05T15:57:48.427881+00:00"},"6DNUHqUJamGuzm9BfBEY\u002Bdy9CuCczQLO/d\u002B6mXa3vH8=":{"Identity":"D:\\Back-end_CuoiKy\\Nam3\\lap-trinh-web\\wwwroot\\script.js","SourceId":"lap_trinh_web","SourceType":"Discovered","ContentRoot":"D:\\Back-end_CuoiKy\\Nam3\\lap-trinh-web\\wwwroot\\","BasePath":"_content/lap_trinh_web","RelativePath":"script#[.{fingerprint}]?.js","AssetKind":"All","AssetMode":"All","AssetRole":"Primary","AssetMergeBehavior":null,"AssetMergeSource":"","RelatedAsset":null,"AssetTraitName":null,"AssetTraitValue":null,"Fingerprint":"wnt9efidhr","Integrity":"bMjCmZQWVwlZK5hdodH6CsgU\u002BFL\u002B9oyHuvC7tNm/R50=","CopyToOutputDirectory":"Never","CopyToPublishDirectory":"PreserveNewest","OriginalItemSpec":"wwwroot\\script.js","FileLength":4424,"LastWriteTime":"2026-03-05T15:57:52.6044263+00:00"},"Bwps20IR269pNgeOYqWYrUhUWY2KnE0/MluM4lIZN9w=":{"Identity":"D:\\Back-end_CuoiKy\\Nam3\\lap-trinh-web\\wwwroot\\style.css","SourceId":"lap_trinh_web","SourceType":"Discovered","ContentRoot":"D:\\Back-end_CuoiKy\\Nam3\\lap-trinh-web\\wwwroot\\","BasePath":"_content/lap_trinh_web","RelativePath":"style#[.{fingerprint}]?.css","AssetKind":"All","AssetMode":"All","AssetRole":"Primary","AssetMergeBehavior":null,"AssetMergeSource":"","RelatedAsset":null,"AssetTraitName":null,"AssetTraitValue":null,"Fingerprint":"u7n8r1vzih","Integrity":"dokfycCLR7L4PfWk4P8GyZli\u002BQpgqngHWeepq3bIXC4=","CopyToOutputDirectory":"Never","CopyToPublishDirectory":"PreserveNewest","OriginalItemSpec":"wwwroot\\style.css","FileLength":1605,"LastWriteTime":"2026-03-05T15:57:52.6044263+00:00"}},"CachedCopyCandidates":{}}